imagestack/__init__.py
imagestack/animated_layers.py
imagestack/colors.py
imagestack/helpers.py
imagestack/imagecreator.py
imagestack/imageresolve.py
imagestack/imagestack.py
imagestack/layers.py
imagestack/loaders.py
imagestack/variables.py
imagestack/visitor.py
imagestack/visitor_create.py
imagestack/visitor_html.py
ImageStack-0.1.24.dist-info/LICENSE
ImageStack-0.1.24.dist-info/METADATA
ImageStack-0.1.24.dist-info/WHEEL
ImageStack-0.1.24.dist-info/top_level.txt
ImageStack-0.1.24.dist-info/RECORD
