Metadata-Version: 2.1
Name: ImageStack
Version: 0.1.24
Summary: Create Images by Stacking them
Home-page: https://github.com/skillor/imagestack-python
Author: skillor
Author-email: skillor@gmx.net
License: MIT
Keywords: image,imagestack
Platform: UNKNOWN
Classifier: Programming Language :: Python :: 3 :: Only
Classifier: Programming Language :: Python :: 3.9
Classifier: Topic :: Multimedia :: Graphics
Requires-Python: >=3
License-File: LICENSE
Requires-Dist: opencv-python (~=4.5.2)
Requires-Dist: numpy (~=1.20)
Requires-Dist: requests (~=2.25)
Requires-Dist: Pillow (~=9.0.1)
